README.md
setup.py
force/__init__.py
force/receptive_field.py
force.egg-info/PKG-INFO
force.egg-info/SOURCES.txt
force.egg-info/dependency_links.txt
force.egg-info/top_level.txt