Metadata-Version: 2.1
Name: force
Version: 0.1.4
Summary: A method for visualizing the receiptive fields of a neural network
Home-page: https://pypi.org/project/force/
Author: Mat Kallada
Author-email: matkallada@gmail.com
License: UNKNOWN
Keywords: machine learning,logging,example
Platform: UNKNOWN
